winwifi/__init__.py
winwifi/__main__.py
winwifi/main.py
winwifi/data/profile-template.xml
winwifi-0.0.9.dist-info/DESCRIPTION.rst
winwifi-0.0.9.dist-info/METADATA
winwifi-0.0.9.dist-info/RECORD
winwifi-0.0.9.dist-info/WHEEL
winwifi-0.0.9.dist-info/entry_points.txt
winwifi-0.0.9.dist-info/metadata.json
winwifi-0.0.9.dist-info/top_level.txt
