Metadata-Version: 2.0
Name: winwifi
Version: 0.0.9
Summary: A Windows Wi-Fi CLI
Home-page: https://github.com/changyuheng/winwifi
Author: Henry Chang
Author-email: mr.changyuheng@gmail.com
License: MIT
Platform: UNKNOWN
Classifier: Development Status :: 3 - Alpha
Classifier: Intended Audience :: System Administrators
Classifier: Topic :: Utilities
Classifier: License :: OSI Approved :: MIT License
Classifier: Programming Language :: Python :: 3.6
Classifier: Environment :: Win32 (MS Windows)
Requires-Python: >=3.6
Requires-Dist: plumbum
Provides-Extra: dev
Requires-Dist: check-manifest; extra == 'dev'
Provides-Extra: test
Requires-Dist: coverage; extra == 'test'
